opentelemetry/exporter/otlp/proto/grpc/__init__.py
opentelemetry/exporter/otlp/proto/grpc/exporter.py
opentelemetry/exporter/otlp/proto/grpc/version.py
opentelemetry/exporter/otlp/proto/grpc/_log_exporter/__init__.py
opentelemetry/exporter/otlp/proto/grpc/metric_exporter/__init__.py
opentelemetry/exporter/otlp/proto/grpc/trace_exporter/__init__.py
opentelemetry_exporter_otlp_proto_grpc-1.12.0.dist-info/LICENSE
opentelemetry_exporter_otlp_proto_grpc-1.12.0.dist-info/METADATA
opentelemetry_exporter_otlp_proto_grpc-1.12.0.dist-info/WHEEL
opentelemetry_exporter_otlp_proto_grpc-1.12.0.dist-info/entry_points.txt
opentelemetry_exporter_otlp_proto_grpc-1.12.0.dist-info/top_level.txt
opentelemetry_exporter_otlp_proto_grpc-1.12.0.dist-info/RECORD
